Workbook
Name Срез_Годы__order_date1: #N/A
Name Срез_product_category1: #N/A
Name Срез_Годы__order_date: #N/A

Sheet Dashboard

Sheet ecommerce_sales_ver_2.0
A1: order_id | B1: order_date | C1: customer_id | D1: customer_name | E1: Gender | F1: City | G1: product_category | H1: quantity | I1: unit_price | J1: discount | K1: payment_method | L1: cust_rating | M1: customer_rating | N1: revenue | O1: total before discount
A2: 10001 | B2: 44562 | C2: 1102 | D2: =_xlfn.XLOOKUP($C2,customers!$A$2:$A$2000,customers!$B$2:$B$2000) -> Bria Rizzone | E2: =_xlfn.XLOOKUP($C2,customers!$A$2:$A$2000,customers!$D$2:$D$2000) -> Female | F2: =_xlfn.XLOOKUP($C2,customers!$A$2:$A$2000,customers!$E$2:$E$2000) -> Prague | G2: Beauty | H2: 7 | I2: 373.65 | J2: 0.28 | K2: Wallet | L2: {=_xlfn.IFS(M2<=3,"BAD",M2>=4.7,"GOOD",AND(M2>3,M2<4.7),"OK")} -> GOOD | M2: 4.7 | N2: 1883.2 | O2: =H2*I2 -> 2615.55
A3: 10002 | B3: 44563 | C3: 1435 | D3: =_xlfn.XLOOKUP($C3,customers!$A$2:$A$2000,customers!$B$2:$B$2000) -> Cami Mylan | E3: =_xlfn.XLOOKUP($C3,customers!$A$2:$A$2000,customers!$D$2:$D$2000) -> Female | F3: =_xlfn.XLOOKUP($C3,customers!$A$2:$A$2000,customers!$E$2:$E$2000) -> Yaté-Barrage | G3: Clothing | H3: 7 | I3: 47.74 | J3: 0.09 | K3: Card | L3: {=_xlfn.IFS(M3<=3,"BAD",M3>=4.7,"GOOD",AND(M3>3,M3<4.7),"OK")} -> OK | M3: 3.9 | N3: 304.1 | O3: =H3*I3 -> 334.18
A4: 10003 | B4: 44563 | C4: 1942 | D4: =_xlfn.XLOOKUP($C4,customers!$A$2:$A$2000,customers!$B$2:$B$2000) -> Rozanne Katzmann | E4: =_xlfn.XLOOKUP($C4,customers!$A$2:$A$2000,customers!$D$2:$D$2000) -> Female | F4: =_xlfn.XLOOKUP($C4,customers!$A$2:$A$2000,customers!$E$2:$E$2000) -> Austin | G4: Clothing | H4: 5 | I4: 514.84 | J4: 0.06 | K4: COD | L4: {=_xlfn.IFS(M4<=3,"BAD",M4>=4.7,"GOOD",AND(M4>3,M4<4.7),"OK")} -> OK | M4: 4.2 | N4: 2419.75 | O4: =H4*I4 -> 2574.2
A5: 10004 | B5: 44563 | C5: 1906 | D5: =_xlfn.XLOOKUP($C5,customers!$A$2:$A$2000,customers!$B$2:$B$2000) -> Betsey Hannibal | E5: =_xlfn.XLOOKUP($C5,customers!$A$2:$A$2000,customers!$D$2:$D$2000) -> Female | F5: =_xlfn.XLOOKUP($C5,customers!$A$2:$A$2000,customers!$E$2:$E$2000) -> Cipicung | G5: Electronics | H5: 3 | I5: 443.97 | J5: 0.3 | K5: COD | L5: {=_xlfn.IFS(M5<=3,"BAD",M5>=4.7,"GOOD",AND(M5>3,M5<4.7),"OK")} -> BAD | M5: 2.9 | N5: 932.34 | O5: =H5*I5 -> 1331.91
A6: 10005 | B6: 44563 | C6: 1963 | D6: =_xlfn.XLOOKUP($C6,customers!$A$2:$A$2000,customers!$B$2:$B$2000) -> Cristina Betho | E6: =_xlfn.XLOOKUP($C6,customers!$A$2:$A$2000,customers!$D$2:$D$2000) -> Female | F6: =_xlfn.XLOOKUP($C6,customers!$A$2:$A$2000,customers!$E$2:$E$2000) -> Bofuer | G6: Beauty | H6: 7 | I6: 391.34 | J6: 0.27 | K6: COD | L6: {=_xlfn.IFS(M6<=3,"BAD",M6>=4.7,"GOOD",AND(M6>3,M6<4.7),"OK")} -> BAD | M6: 1.9 | N6: 1999.75 | O6: =H6*I6 -> 2739.38
A7: 10006 | B7: 44564 | C7: 1860 | D7: =_xlfn.XLOOKUP($C7,customers!$A$2:$A$2000,customers!$B$2:$B$2000) -> Tildi Carayol | E7: =_xlfn.XLOOKUP($C7,customers!$A$2:$A$2000,customers!$D$2:$D$2000) -> Female | F7: =_xlfn.XLOOKUP($C7,customers!$A$2:$A$2000,customers!$E$2:$E$2000) -> Austin | G7: Beauty | H7: 3 | I7: 311.28 | J7: 0.31 | K7: COD | L7: {=_xlfn.IFS(M7<=3,"BAD",M7>=4.7,"GOOD",AND(M7>3,M7<4.7),"OK")} -> BAD | M7: 2.5 | N7: 644.35 | O7: =H7*I7 -> 933.84
A8: 10007 | B8: 44564 | C8: 1824 | D8: =_xlfn.XLOOKUP($C8,customers!$A$2:$A$2000,customers!$B$2:$B$2000) -> Layney Mozzi | E8: =_xlfn.XLOOKUP($C8,customers!$A$2:$A$2000,customers!$D$2:$D$2000) -> Female | F8: =_xlfn.XLOOKUP($C8,customers!$A$2:$A$2000,customers!$E$2:$E$2000) -> Milan | G8: Beauty | H8: 6 | I8: 87.6 | J8: 0.23 | K8: Card | L8: {=_xlfn.IFS(M8<=3,"BAD",M8>=4.7,"GOOD",AND(M8>3,M8<4.7),"OK")} -> OK | M8: 3.8 | N8: 404.71 | O8: =H8*I8 -> 525.6
A9: 10008 | B9: 44564 | C9: 1803 | D9: =_xlfn.XLOOKUP($C9,customers!$A$2:$A$2000,customers!$B$2:$B$2000) -> Paolo Mersh | E9: =_xlfn.XLOOKUP($C9,customers!$A$2:$A$2000,customers!$D$2:$D$2000) -> Male | F9: =_xlfn.XLOOKUP($C9,customers!$A$2:$A$2000,customers!$E$2:$E$2000) -> Hongjiang | G9: Clothing | H9: 5 | I9: 59.52 | J9: 0.06 | K9: Card | L9: {=_xlfn.IFS(M9<=3,"BAD",M9>=4.7,"GOOD",AND(M9>3,M9<4.7),"OK")} -> BAD | M9: 2.2 | N9: 279.74 | O9: =H9*I9 -> 297.6
A10: 10009 | B10: 44564 | C10: 1265 | D10: =_xlfn.XLOOKUP($C10,customers!$A$2:$A$2000,customers!$B$2:$B$2000) -> Katerina Lynch | E10: =_xlfn.XLOOKUP($C10,customers!$A$2:$A$2000,customers!$D$2:$D$2000) -> Female | F10: =_xlfn.XLOOKUP($C10,customers!$A$2:$A$2000,customers!$E$2:$E$2000) -> Mollas | G10: Electronics | H10: 2 | I10: 59.79 | J10: 0.33 | K10: COD | L10: {=_xlfn.IFS(M10<=3,"BAD",M10>=4.7,"GOOD",AND(M10>3,M10<4.7),"OK")} -> BAD | M10: 2.5 | N10: 80.12 | O10: =H10*I10 -> 119.58
A11: 10010 | B11: 44565 | C11: 1270 | D11: =_xlfn.XLOOKUP($C11,customers!$A$2:$A$2000,customers!$B$2:$B$2000) -> Emmit Tindley | E11: =_xlfn.XLOOKUP($C11,customers!$A$2:$A$2000,customers!$D$2:$D$2000) -> Male | F11: =_xlfn.XLOOKUP($C11,customers!$A$2:$A$2000,customers!$E$2:$E$2000) -> Milan | G11: Electronics | H11: 5 | I11: 524.47 | J11: 0.02 | K11: Wallet | L11: {=_xlfn.IFS(M11<=3,"BAD",M11>=4.7,"GOOD",AND(M11>3,M11<4.7),"OK")} -> BAD | M11: 1.6 | N11: 2569.9 | O11: =H11*I11 -> 2622.35
A12: 10011 | B12: 44566 | C12: 1106 | D12: =_xlfn.XLOOKUP($C12,customers!$A$2:$A$2000,customers!$B$2:$B$2000) -> Ingeberg Dugall | E12: =_xlfn.XLOOKUP($C12,customers!$A$2:$A$2000,customers!$D$2:$D$2000) -> Female | F12: =_xlfn.XLOOKUP($C12,customers!$A$2:$A$2000,customers!$E$2:$E$2000) -> Yanghuxiang | G12: Clothing | H12: 5 | I12: 139.87 | J12: 0.33 | K12: Wallet | L12: {=_xlfn.IFS(M12<=3,"BAD",M12>=4.7,"GOOD",AND(M12>3,M12<4.7),"OK")} -> GOOD | M12: 4.9 | N12: 468.56 | O12: =H12*I12 -> 699.35
A13: 10012 | B13: 44566 | C13: 1683 | D13: =_xlfn.XLOOKUP($C13,customers!$A$2:$A$2000,customers!$B$2:$B$2000) -> Hirsch Watkiss | E13: =_xlfn.XLOOKUP($C13,customers!$A$2:$A$2000,customers!$D$2:$D$2000) -> Male | F13: =_xlfn.XLOOKUP($C13,customers!$A$2:$A$2000,customers!$E$2:$E$2000) -> Budapest | G13: Electronics | H13: 6 | I13: 323.43 | J13: 0.05 | K13: COD | L13: {=_xlfn.IFS(M13<=3,"BAD",M13>=4.7,"GOOD",AND(M13>3,M13<4.7),"OK")} -> OK | M13: 4.2 | N13: 1843.55 | O13: =H13*I13 -> 1940.58
... A5001: 15000 | B5001: 46387 | C5001: 1837 | D5001: =_xlfn.XLOOKUP($C5001,customers!$A$2:$A$2000,customers!$B$2:$B$2000) -> Andra Oldroyde | E5001: =_xlfn.XLOOKUP($C5001,customers!$A$2:$A$2000,customers!$D$2:$D$2000) -> Female | F5001: =_xlfn.XLOOKUP($C5001,customers!$A$2:$A$2000,customers!$E$2:$E$2000) -> Werasari | G5001: Beauty | H5001: 4 | I5001: 486.45 | J5001: 0.19 | K5001: Card | L5001: {=_xlfn.IFS(M5001<=3,"BAD",M5001>=4.7,"GOOD",AND(M5001>3,M5001<4.7),"OK")} -> BAD | M5001: 2.4 | N5001: 1576.1 | O5001: =H5001*I5001 -> 1945.8

Sheet customers
A1: customer_id | B1: customer_name | C1: email | D1: gender | E1: address
A2: 1000 | B2: Lyndsie Ralling | C2: lralling0@51.la | D2: Female | E2: Paris
A3: 1001 | B3: Lyell Donaghy | C3: ldonaghy1@disqus.com | D3: Male | E3: Milan
A4: 1002 | B4: Elise McGlew | C4: emcglew2@list-manage.com | D4: Female | E4: Tallinn
A5: 1003 | B5: Jaymie Ladson | C5: jladson3@goo.gl | D5: Male | E5: Berber
A6: 1004 | B6: Taber Lewendon | C6: tlewendon4@ebay.com | D6: Male | E6: Västervik
A7: 1005 | B7: Nico McGirr | C7: nmcgirr5@bandcamp.com | D7: Male | E7: Vienna
A8: 1006 | B8: Emma Birtwhistle | C8: ebirtwhistle6@sitemeter.com | D8: Female | E8: Paris 20
A9: 1007 | B9: Tally Pettet | C9: tpettet7@jigsy.com | D9: Female | E9: Budapest
A10: 1008 | B10: Clemens Gemlbett | C10: cgemlbett8@over-blog.com | D10: Male | E10: Oslo
A11: 1009 | B11: Quinton Assur | C11: qassur9@squarespace.com | D11: Male | E11: Budapest
A12: 1010 | B12: Jessie Gallety | C12: jgalletya@go.com | D12: Male | E12: Brignoles
A13: 1011 | B13: Drucy Dillintone | C13: ddillintoneb@shinystat.com | D13: Female | E13: Vienna
... A2000: 2998 | B2000: Hewett Kener | C2000: hkenerrq@cargocollective.com | D2000: Male | E2000: Bluefields

Sheet Rev by Pr Cat a year
A2: Годы (order_date) | B2: 2025
A4: product_category | B4: Сумма revenue
A5: Beauty | B5: 157653.32
A6: Clothing | B6: 357057.54
A7: Electronics | B7: 439477.35
A8: Home | B8: 195976.75
A9: Общий итог | B9: 1150165

Sheet Rev_Qant
A2: Годы (order_date) | B2: 2025
A4: product_category | B4: Сумма quantity | C4: Сумма revenue
A5: Beauty | B5: 627 | C5: 157653.32
A6: Clothing | B6: 1415 | C6: 357057.54
A7: Electronics | B7: 1678 | C7: 439477.35
A8: Home | B8: 830 | C8: 195976.75
A9: Общий итог | B9: 4550 | C9: 1150165

Sheet Rev by Pr Cat by Month
A3: Сумма revenue | C3: product_category
A4: Годы (order_date) | B4: order_date | C4: Electronics | D4: Общий итог
A5: 2025
B6: Jan | C6: 28645.34 | D6: 28645.34
B7: Feb | C7: 39146.97 | D7: 39146.97
B8: Mar | C8: 39218.6 | D8: 39218.6
B9: Apr | C9: 37739.54 | D9: 37739.54
B10: May | C10: 33320.91 | D10: 33320.91
B11: Jun | C11: 44332.27 | D11: 44332.27
B12: Jul | C12: 49231.63 | D12: 49231.63
B13: Aug | C13: 25740.71 | D13: 25740.71
B14: Sep | C14: 43422.24 | D14: 43422.24
B15: Oct | C15: 32606.69 | D15: 32606.69
B16: Nov | C16: 23712.27 | D16: 23712.27
B17: Dec | C17: 42360.18 | D17: 42360.18
A18: Общий итог | C18: 439477.35 | D18: 439477.35

Sheet Top 10 Cities 
A3: Сумма revenue | B3: product_category
A4: City | B4: Electronics | C4: Общий итог
A5: Ulyanovsk | B5: 9879.44 | C5: 9879.44
A6: Ochër | B6: 10118.06 | C6: 10118.06
A7: Belgrade | B7: 14369.11 | C7: 14369.11
A8: Vienna | B8: 28429.18 | C8: 28429.18
A9: Tallinn | B9: 29669.85 | C9: 29669.85
A10: Paris | B10: 47881.97 | C10: 47881.97
A11: Austin | B11: 92166.69 | C11: 92166.69
A12: Prague | B12: 122651.18 | C12: 122651.18
A13: Milan | B13: 168223.59 | C13: 168223.59
A14: Budapest | B14: 232432.93 | C14: 232432.93
A15: Общий итог | B15: 755822 | C15: 755822

Sheet Revenue by Gender
A4: Сумма revenue | B4: product_category | C4: Gender
B5: Electronics | D5: Итого Electronics | E5: Общий итог
A6: Годы (order_date) | B6: Female | C6: Male
A7: 2022 | B7: 193721.51 | C7: 219148.69 | D7: 412870.2 | E7: 412870.2
A8: 2023 | B8: 190434.67 | C8: 203664.56 | D8: 394099.23 | E8: 394099.23
A9: 2024 | B9: 210332.24 | C9: 219723.1 | D9: 430055.34 | E9: 430055.34
A10: 2025 | B10: 248789.19 | C10: 190688.16 | D10: 439477.35 | E10: 439477.35
A11: 2026 | B11: 69170.09 | C11: 84227.37 | D11: 153397.46 | E11: 153397.46
A12: Общий итог | B12: 912447.7 | C12: 917451.88 | D12: 1829899.6 | E12: 1829899.6

Sheet Revenue by Rating
A3: Сумма revenue | B3: product_category
A4: cust_rating | B4: Electronics | C4: Общий итог
A5: BAD | B5: 967132.37 | C5: 967132.37
A6: GOOD | B6: 135357.12 | C6: 135357.12
A7: OK | B7: 727410.09 | C7: 727410.09
A8: Общий итог | B8: 1829899.6 | C8: 1829899.6
A12: Rating | C12: Clothing | D12: Electronics | E12: Home
A13: BAD | B13: {=_xlfn.XLOOKUP($A$13,$A$5:$A$8,$B$5:$E$8)} -> 967132.37 | C13: 967132.37 | D13: 0 | E13: 0
A14: OK | B14: {=_xlfn.XLOOKUP($A$14,$A$5:$A$8,$B$5:$E$8)} -> 727410.09 | C14: 727410.09 | D14: 0 | E14: 0
A15: GOOD | B15: {=_xlfn.XLOOKUP($A$15,$A$5:$A$8,$B$5:$E$8)} -> 135357.12 | C15: 135357.12 | D15: 0 | E15: 0
